odoo/addons/mail_no_user_assign_notification/README.rst
odoo/addons/mail_no_user_assign_notification/__init__.py
odoo/addons/mail_no_user_assign_notification/__manifest__.py
odoo/addons/mail_no_user_assign_notification/data/ir_config_parameter.xml
odoo/addons/mail_no_user_assign_notification/i18n/es.po
odoo/addons/mail_no_user_assign_notification/i18n/it.po
odoo/addons/mail_no_user_assign_notification/i18n/mail_no_user_assign_notification.pot
odoo/addons/mail_no_user_assign_notification/models/__init__.py
odoo/addons/mail_no_user_assign_notification/models/mail_thread.py
odoo/addons/mail_no_user_assign_notification/readme/CONFIGURE.md
odoo/addons/mail_no_user_assign_notification/readme/CONTRIBUTORS.md
odoo/addons/mail_no_user_assign_notification/readme/DESCRIPTION.md
odoo/addons/mail_no_user_assign_notification/readme/ROADMAP.md
odoo/addons/mail_no_user_assign_notification/readme/USAGE.md
odoo/addons/mail_no_user_assign_notification/static/description/icon.png
odoo/addons/mail_no_user_assign_notification/static/description/index.html
odoo/addons/mail_no_user_assign_notification/tests/__init__.py
odoo/addons/mail_no_user_assign_notification/tests/test_mail_no_user_assign_notification.py
odoo_addon_mail_no_user_assign_notification-17.0.1.0.0.4.dist-info/METADATA
odoo_addon_mail_no_user_assign_notification-17.0.1.0.0.4.dist-info/WHEEL
odoo_addon_mail_no_user_assign_notification-17.0.1.0.0.4.dist-info/top_level.txt
odoo_addon_mail_no_user_assign_notification-17.0.1.0.0.4.dist-info/RECORD
